LICENSE
MANIFEST.in
README.md
requirements.txt
setup.cfg
setup.py
docker_registry/__init__.py
docker_registry/../config/config.yml
docker_registry/drivers/__init__.py
docker_registry/drivers/cassandra.py
docker_registry_driver_cassandra.egg-info/PKG-INFO
docker_registry_driver_cassandra.egg-info/SOURCES.txt
docker_registry_driver_cassandra.egg-info/dependency_links.txt
docker_registry_driver_cassandra.egg-info/namespace_packages.txt
docker_registry_driver_cassandra.egg-info/requires.txt
docker_registry_driver_cassandra.egg-info/top_level.txt
docker_registry_driver_cassandra.egg-info/zip-safe