Metadata-Version: 1.1
Name: docker-registry-driver-cassandra
Version: 0.1.3
Summary: Docker registry driver for cassandra
Home-page: https://github.com/milaw/docker-registry-driver-cassandra
Author: Milaw
Author-email: gmilaw@gmail.com
License: The MIT License (MIT)
